ping_multi_ext/__init__.py
ping_multi_ext/cmd_multi.py
ping_multi_ext/cmd_raw.py
ping_multi_ext/core.py
ping_multi_ext/lib.py
ping_multi_ext/proc.py
ping_multi_ext-1.2.0.dist-info/LICENSE
ping_multi_ext-1.2.0.dist-info/METADATA
ping_multi_ext-1.2.0.dist-info/WHEEL
ping_multi_ext-1.2.0.dist-info/entry_points.txt
ping_multi_ext-1.2.0.dist-info/top_level.txt
ping_multi_ext-1.2.0.dist-info/RECORD
