Metadata-Version: 2.2
Name: ping-multi-ext
Version: 1.2.0
Summary: Interactively ping one or many hosts from one or multiple locations (locally or via SSH)
Home-page: https://github.com/famzah/ping-multi-ext
Author: Ivan Zahariev (famzah)
Project-URL: Bug Reports, https://github.com/famzah/ping-multi-ext/issues
Project-URL: Source, https://github.com/famzah/ping-multi-ext
Keywords: ping,multi,console,ssh,terminal,interactive
Classifier: Development Status :: 5 - Production/Stable
Classifier: Environment :: Console
Classifier: Intended Audience :: System Administrators
Classifier: License :: OSI Approved :: MIT License
Classifier: Operating System :: POSIX :: Linux
Classifier: Programming Language :: Python :: 3
Classifier: Programming Language :: Python :: 3 :: Only
Classifier: Programming Language :: Python :: 3.6
Classifier: Programming Language :: Python :: 3.7
Classifier: Programming Language :: Python :: 3.8
Classifier: Programming Language :: Python :: 3.9
Classifier: Topic :: Internet
Classifier: Topic :: System :: Networking :: Monitoring
Classifier: Topic :: Terminals
Classifier: Topic :: Utilities
Requires-Python: >=3.6, <4
License-File: LICENSE
Requires-Dist: blessings
Requires-Dist: curtsies
Dynamic: author
Dynamic: classifier
Dynamic: description
Dynamic: description-content-type
Dynamic: home-page
Dynamic: keywords
Dynamic: project-url
Dynamic: requires-dist
Dynamic: requires-python
Dynamic: summary
